LICENSE.txt
MANIFEST.in
README.md
setup.cfg
setup.py
pymycustomlinearmodel/__init__.py
pymycustomlinearmodel/custom_logger.py
pymycustomlinearmodel/linear_model.py
pymycustomlinearmodel/requirements.txt
pymycustomlinearmodel.egg-info/PKG-INFO
pymycustomlinearmodel.egg-info/SOURCES.txt
pymycustomlinearmodel.egg-info/dependency_links.txt
pymycustomlinearmodel.egg-info/requires.txt
pymycustomlinearmodel.egg-info/top_level.txt