Metadata-Version: 2.1
Name: pymycustomlinearmodel
Version: 0.1
Summary: Simple Linear Regression Model
Home-page: UNKNOWN
Author: Pallavi Saxena
Author-email: pallavi.as1127@gmail.com
License: MIT
Keywords: EDA
Platform: UNKNOWN
Classifier: Development Status :: 3 - Alpha
License-File: LICENSE.txt
